e2_tts_pytorch/__init__.py
e2_tts_pytorch/e2_tts.py
e2_tts_pytorch/trainer.py
e2_tts_pytorch-2.2.2.dist-info/METADATA
e2_tts_pytorch-2.2.2.dist-info/WHEEL
e2_tts_pytorch-2.2.2.dist-info/licenses/LICENSE
e2_tts_pytorch-2.2.2.dist-info/RECORD
