Metadata-Version: 2.4
Name: e2-tts-pytorch
Version: 2.2.2
Summary: E2-TTS in Pytorch
Project-URL: Homepage, https://pypi.org/project/e2-tts-pytorch/
Project-URL: Repository, https://github.com/lucidrains/e2-tts-pytorch
Author-email: Phil Wang <lucidrains@gmail.com>
License: MIT License
License-File: LICENSE
Keywords: artificial intelligence,attention mechanism,deep learning,text to speech,transformers
Classifier: Development Status :: 4 - Beta
Classifier: Intended Audience :: Developers
Classifier: License :: OSI Approved :: MIT License
Classifier: Programming Language :: Python :: 3.8
Classifier: Topic :: Scientific/Engineering :: Artificial Intelligence
Requires-Python: >=3.8
Requires-Dist: accelerate>=0.33.0
Requires-Dist: adam-atan2-pytorch>=0.1.12
Requires-Dist: beartype
Requires-Dist: einops>=0.8.0
Requires-Dist: einx>=0.3.0
Requires-Dist: ema-pytorch>=0.5.2
Requires-Dist: g2p-en
Requires-Dist: hl-gauss-pytorch>=0.1.7
Requires-Dist: hyper-connections>=0.0.10
Requires-Dist: jaxtyping
Requires-Dist: loguru
Requires-Dist: pydantic<2
Requires-Dist: tensorboard
Requires-Dist: torch>=2.0
Requires-Dist: torchaudio>=2.3.1
Requires-Dist: torchdiffeq
Requires-Dist: tqdm>=4.65.0
Requires-Dist: vocos
Requires-Dist: x-transformers>=1.42.23
Provides-Extra: examples
Requires-Dist: datasets; extra == 'examples'
